{
    "date": "2025-01-18",
    "title_en": "Moving on myth.",
    "title_it": "Procedendo nel mito.",
    "poem_en": "Her eyes, clouded, brimming— a cup overflowing. My words, though worn, let me try once more; the tears return, but the thoughts never fade; a heart beating never stills— a stubborn pulse remains. Written to GoGo Penguin - Hopopono.",
    "poem_it": "I suoi occhi, offuscati, traboccanti— come una tazza che tracima. Le mie parole, seppur logorate, permettimi di provare ancora una volta; le lacrime ritornano, ma i pensieri non svaniscono mai; un cuore che batte, mai quieto— un'ostinata pulsazione permane. Scritto per GoGo Penguin - Hopopono.",
    "category": "Bluesky"
}