{
    "date": "20241224",
    "title_en": "Wish You The Best.",
    "title_it": "Ti Auguro Il Meglio",
    "poem_en": "There’s a moment I cherish where the scent of coffee lingers,\nA book left behind and the gentle touch of soft fingers.\nA rhyme hums its melody, faint upon the air,\nWhispers of memories draped in silent despair.\n\nThe strangest of things is how time marches on,\nIts lines keep unfolding, though the words are gone.\nA piano’s keys sit silent, devoid of tune,\nMy symphony echoes beneath the silver moon.\n\nFor each star that glimmers and pierces through the night,\nA million words bloom, chasing shadows with light.\nEmotions find refuge in the depths of the heart,\nWhere longing persists, though we’re oceans apart.\n\nIf all I remember are glimpses of you,\nThen beauty suffices, for memories stay true.\nYet one wish remains as these lines draw to end:\nThat you always have happiness, books, and laughs.",
    "poem_it": "C'è un istante che serbo, ove l'aroma di caffè indugia,\nUn libro dimenticato, e il tocco lieve di dita delicate.\nUna rima sussurra la sua melodia, tenue nell'aria,\nSospiri di memorie avvolte in silente malinconia.\n\nLa cosa più strana è come il tempo inesorabile avanzi,\nLe sue linee si dipanano, sebbene le parole siano svanite.\nI tasti di un piano tacciono, privi di melodia,\nLa mia sinfonia echeggia sotto la luna argentea.\n\nPer ogni stella che brilla e trafigge la notte,\nUn milione di parole sbocciano, cacciando ombre con luce.\nLe emozioni trovano rifugio nel profondo del cuore,\nDove il desiderio persiste, sebbene oceani ci separino.\n\nSe tutto ciò che ricordo sono fugaci scorci di te,\nAllora la bellezza è sufficiente, poiché i ricordi restano veri.\nEppure un desiderio rimane, mentre questi versi volgono al termine:\nChe tu possa sempre avere felicità, libri e risate.",
    "tags": [
        "longform",
        "sad",
        "loving",
        "longing",
        "melancholy"
    ]
}