{
    "date": "2025-01-01",
    "title_en": "My Wheelhouse.",
    "title_it": "La Mia Competenza.",
    "poem_en": "Paranoia, connections, words, reflections, emotions, inflections, heartbeat, reactions, palpitations, emotions, nervousness, excitations, breathe.",
    "poem_it": "Paranoia, connessioni, parole, riflessioni, emozioni, inflessioni, battito, reazioni, palpitazioni, emozioni, nervosismo, eccitazioni, respirare.",
    "category": "Bluesky",
    "tags": [
        "longform",
        "dark",
        "tender",
        "melancholy"
    ]
}