{
    "date": "2025-02-02",
    "title_en": "Maple.",
    "title_it": "Acero.",
    "poem_en": "Wrapped in rings, constantly bound, a pressure encircling, marking each passing year. Tapped during winter for my very blood— the needle runs deep and out draws the ink. I am but a bastion of sap, on tap for your delight. Stick out your tongue and have but a taste.",
    "poem_it": "Avvolto in anelli, costantemente legato, una pressione che circonda, segna ogni anno che passa. Sfiorato durante l'inverno per il mio stesso sangue — l'ago si insinua profondamente e tira fuori l'inchiostro. Io sono soltanto una roccaforte di linfa, a tua disposizione per il tuo piacere. Sbatti fuori la lingua e assaggia soltanto un po'.",
    "category": "Half_baked_prompts",
    "tags": [
        "longform",
        "dark",
        "melancholy",
        "whimsical"
    ]
}