{
    "date": "2025-02-21",
    "title_en": "Old Brew.",
    "title_it": "Vecchio Liquore.",
    "poem_en": "Carving vernacular, axe to jugular. Action figure—wind-up action, of morbid erasure and a contemplative nature. It's a meal, it was a feast—and a forever stew. A beast of a last supper, now released, crawled from the cauldron stewing.",
    "poem_it": "Intagliando il vernacolo, ascia alla giugulare. Figura d'azione - a carica, di cancellazione morbida e natura contemplativa. Era un pasto, era una festa - e uno stufato eterno. Una bestia di un'ultima cena, ora liberata, strisciava dal calderone che ribolliva.",
    "category": "Hedges"
}