{
    "date": "2025-02-21",
    "title_en": "Terminal pangs.",
    "title_it": "Dolori terminali.",
    "poem_en": "Carl was congested. Normally not such a bad thing, but he didn’t just have a heart, he was one. While some try, he lived his whole life with it, not just on his sleeve. It was terminal, you see. He missed a flight. She was on it, there was no catching up. Skipped a beat without him even noticing.",
    "poem_it": "Carlo era afflitto. Di solito non sarebbe stato così grave, ma lui non possedeva solo un cuore, lui era un cuore. Mentre alcuni tentano, lui visse la sua intera vita con questo peso, non soltanto in superficie. Era una condanna a morte, si può dire. Ha perso un volo. Lei era su di esso, e non c'era modo di raggiungerla. Il suo cuore ha vacillato senza che lui se ne accorgesse.",
    "category": "Hedges"
}