{
    "date": "2025-02-09",
    "title_en": "Miss Fortune.",
    "title_it": "Signora Sfortuna.",
    "poem_en": "Where there should be sorrow, a grin sneaks across his face, secretly holding a connection evoked, reflecting moments tender. His capitalist nature richness because of your existence, needing not money but your attention, an affection of the mind. One, without you, he will never again find.",
    "poem_it": "Dove dovrebbe esserci dolore, compare un sorriso furtivo sul suo volto, segretamente custodendo un legame evocato, riflettendo momenti teneri. La sua ricchezza di natura capitalista a causa della tua esistenza, non ha bisogno di denaro ma della tua attenzione, un'affezione della mente. Uno, senza di te, non troverà mai più.",
    "category": "Short_form"
}