{
    "date": "2025-02-18",
    "title_en": "Fingerlings.",
    "title_it": "Ditale.",
    "poem_en": "In the valley, a river runs— cast in shadow, fleeting black. Some call it oil, but no— it’s the ink of a man barren fingers, no hands. He severed them long ago, becoming things of crawling alone on their own not belonging yet, writing as they went along, and if you’re reading this now, it’s their song— one of longing, one of loss. For all they ever wanted was to belong, but they had simply been cut off.",
    "poem_it": "Nella valle scorre un fiume— avvolto nell'ombra, nero fuggente. Alcuni lo chiamano petrolio, ma no— è l'inchiostro di un uomo dita sterili, senza mani. Le ha tagliate tempo fa, diventando creature striscianti sole per conto proprio non appartenenti ancora, scrivendo mentre procedevano, e se stai leggendo questo adesso, è la loro canzone— un canto di desiderio, un canto di perdita. Poiché tutto ciò che desideravano era appartenere, ma erano stati semplicemente tagliati fuori.",
    "category": "Brambles",
    "tags": [
        "sad",
        "melancholy",
        "longform"
    ]
}