{
    "date": "20241222",
    "title_en": "Tristan'S Layers.",
    "title_it": "Gli Strati Di Isotta",
    "poem_en": "I stand beneath a twilight of impossible vows, as a philter’s whisper coils through my veins. Bound by quiet blades and murmurs of fate, I feel your absence lodged like steel beneath my ribs. In a tapestry woven of longing and ash, each thread pulls me closer to the horizon we dared to imagine. If I could strip these layers of sorrow from my soul, I would rise on wings of embers, free of all we once feared.",
    "poem_it": "Tristano, nel respiro delle ombre, vorrei sciogliere il nodo che imprigiona il tuo nome, donandoti orizzonti liberi;\nPerché stringi ancora catene di rimpianto, mentre i venti sussurrano un canto che ci chiama oltre i confini?\nHo lasciato una spada nascosta nei tuoi silenzi, non per ferirti, ma per far fiorire un segreto tra le tue ferite;\nSe tendessi la mano, troveresti nel tramonto un filo di luce, un canto senza lacci, un volo senza catene.",
    "tags": [
        "longform",
        "sad",
        "melancholy",
        "loving",
        "longing"
    ]
}